gumpgpd/DVCS_xsec.py
gumpgpd/DVMP_xsec.py
gumpgpd/Evolution.py
gumpgpd/Minimizer.py
gumpgpd/Observables.py
gumpgpd/Parameters.py
gumpgpd/__init__.py
gumpgpd/_helper_.py
gumpgpd/_paragen_.py
gumpgpd/config.py
gumpgpd/GUMPDATA/DVCSAsym.csv
gumpgpd/GUMPDATA/DVCSxsec_HERA.csv
gumpgpd/GUMPDATA/DVCSxsec_New.csv
gumpgpd/GUMPDATA/DVCSxsec_Old.csv
gumpgpd/GUMPDATA/DVCSxsec_Temp.csv
gumpgpd/GUMPDATA/GFFdata.csv
gumpgpd/GUMPDATA/GPDdata.csv
gumpgpd/GUMPDATA/PDFdata.csv
gumpgpd/GUMPDATA/tPDFdata.csv
gumpgpd/GUMPDATA/DVCS_HERA/DVCSH104dt.csv
gumpgpd/GUMPDATA/DVCS_HERA/DVCSH104tot.csv
gumpgpd/GUMPDATA/DVCS_HERA/DVCSH196dt.csv
gumpgpd/GUMPDATA/DVCS_HERA/DVCSH196tot.csv
gumpgpd/GUMPDATA/DVCS_HERA/DVCSH1_0709_4114.csv
gumpgpd/GUMPDATA/DVCS_HERA/DVCSZEUS08dt.csv
gumpgpd/GUMPDATA/DVCS_HERA/DVCSZEUS08tot.csv
gumpgpd/GUMPDATA/DVCS_HERA/DVCSeminusZEUS03tot.csv
gumpgpd/GUMPDATA/DVCS_HERA/DVCSeplusZEUS03tot.csv
gumpgpd/GUMPDATA/DVMP_HERA/DVJpsiPH1dt.csv
gumpgpd/GUMPDATA/DVMP_HERA/DVJpsiPH1dt_w_mass.csv
gumpgpd/GUMPDATA/DVMP_HERA/DVJpsiPZEUSdt.csv
gumpgpd/GUMPDATA/DVMP_HERA/DVJpsiPZEUSdt_w_mass.csv
gumpgpd/GUMPDATA/DVMP_HERA/DVphiPH1dt.csv
gumpgpd/GUMPDATA/DVMP_HERA/DVphiPH1tot.csv
gumpgpd/GUMPDATA/DVMP_HERA/DVphiPZEUSdt.csv
gumpgpd/GUMPDATA/DVMP_HERA/DVphiPZEUStot.csv
gumpgpd/GUMPDATA/DVMP_HERA/DVrhoPH1dt.csv
gumpgpd/GUMPDATA/DVMP_HERA/DVrhoPH1tot.csv
gumpgpd/GUMPDATA/DVMP_HERA/DVrhoPZEUSdt.csv
gumpgpd/GUMPDATA/DVMP_HERA/DVrhoPZEUStot.csv
gumpgpd/GUMPDATA/DVMP_HERA/Jpsi_photo_H1_dt.csv
gumpgpd/GUMPDATA/DVMP_HERA/R_rho_ZEUSnH1.csv
gumpgpd/GUMPDATA/DVMP_HERA/R_rho_ZEUSnH1_w_err.csv
gumpgpd/GUMP_Params/Para_Pol_Off_forward_withH_withHt_NLO.csv
gumpgpd/GUMP_Params/Para_Unp_Off_forward_withH_withHt_NLO.csv
gumpgpd-1.0.0.dist-info/METADATA
gumpgpd-1.0.0.dist-info/WHEEL
gumpgpd-1.0.0.dist-info/licenses/LICENSE
gumpgpd-1.0.0.dist-info/RECORD
