Metadata-Version: 2.4
Name: gumpgpd
Version: 1.0.0
Summary: GPD analysis tools for DVCS, DVMP, and lattice inputs
Author-email: Yuxun Guo <youuungx@gmail.com>
License: MIT
License-File: LICENSE
Classifier: License :: OSI Approved :: MIT License
Classifier: Operating System :: OS Independent
Classifier: Programming Language :: Python :: 3
Requires-Python: >=3.8
Requires-Dist: iminuit
Requires-Dist: joblib
Requires-Dist: mpmath
Requires-Dist: numba
Requires-Dist: numpy
Requires-Dist: pandas
Requires-Dist: scipy
